{
  "citations" : [ {
    "textCitation" : "[See 0ringbas on Metamath](http://us.metamath.org/mpegif/0ringbas.html)"
  } ],
  "argumentText" : "ARGUMENT\n\n| Step | Hyp | Ref | Expression |\n|---|---|---|---|\n\n| 1 |  | 0ringdif.b | |- B = ( Base ` R ) |\n| 2 |  | 0ringdif.0 | |- .0. = ( 0g ` R ) |\n| 3 | 1, 2 | #P_0ringdif | |- ( R e. ( Ring \\ NzRing ) <-> ( R e. Ring /\\ B = { .0. } ) ) |\n| 4 | 3 | #P_simprbi | |- ( R e. ( Ring \\ NzRing ) -> B = { .0. } ) |",
  "conclusion" : "#P_0ringbas",
  "language" : "METAMATH_SET_MM",
  "lookupTerms" : [ "#T_cB", "#T_wceq", "#T_cbs", "#T_cfv", "#T_cR", "#T_c.0", "#T_wceq", "#T_c0g", "#T_cfv", "#T_cR", "#T_cR", "#T_wcel", "#T_crg", "#T_cdif", "#T_cnzr", "#T_wb", "#T_cR", "#T_wcel", "#T_crg", "#T_wa", "#T_cB.wceq", "#T_wceq", "#T_csn--1", "#T_c.0", "#T_csn--2", "#T_cR", "#T_wcel", "#T_crg", "#T_cdif", "#T_cnzr", "#T_wi", "#T_cB", "#T_wceq", "#T_csn--1", "#T_c.0", "#T_csn--2" ],
  "metaLanguage" : "METAMATH",
  "premises" : [ "#P_0ringdif", "#P_simprbi" ]
}