{
  "citations" : [ {
    "textCitation" : "[See logbleb on Metamath](http://us.metamath.org/mpegif/logbleb.html)"
  } ],
  "argumentText" : "ARGUMENT\n\n| Step | Hyp | Ref | Expression |\n|---|---|---|---|\n\n| 1 |  | #P_simp2 | |- ( ( B e. ( ZZ>= ` 2 ) /\\ X e. RR+ /\\ Y e. RR+ ) -> X e. RR+ ) |\n| 2 | 1 | #P_relogcld | |- ( ( B e. ( ZZ>= ` 2 ) /\\ X e. RR+ /\\ Y e. RR+ ) -> ( log ` X ) e. RR ) |\n| 3 |  | #P_simp3 | |- ( ( B e. ( ZZ>= ` 2 ) /\\ X e. RR+ /\\ Y e. RR+ ) -> Y e. RR+ ) |\n| 4 | 3 | #P_relogcld | |- ( ( B e. ( ZZ>= ` 2 ) /\\ X e. RR+ /\\ Y e. RR+ ) -> ( log ` Y ) e. RR ) |\n| 5 |  | #P_eluzelre | |- ( B e. ( ZZ>= ` 2 ) -> B e. RR ) |\n| 6 | 5 | #P_3ad2ant1 | |- ( ( B e. ( ZZ>= ` 2 ) /\\ X e. RR+ /\\ Y e. RR+ ) -> B e. RR ) |\n| 7 |  | #P_1z | |- 1 e. ZZ |\n| 8 |  | #P_simp1 | |- ( ( B e. ( ZZ>= ` 2 ) /\\ X e. RR+ /\\ Y e. RR+ ) -> B e. ( ZZ>= ` 2 ) ) |\n| 9 |  | #P_1p1e2 | |- ( 1 + 1 ) = 2 |\n| 10 | 9 | #P_fveq2i | |- ( ZZ>= ` ( 1 + 1 ) ) = ( ZZ>= ` 2 ) |\n| 11 | 8, 10 | #P_syl6eleqr | |- ( ( B e. ( ZZ>= ` 2 ) /\\ X e. RR+ /\\ Y e. RR+ ) -> B e. ( ZZ>= ` ( 1 + 1 ) ) ) |\n| 12 |  | #P_eluzp1l | |- ( ( 1 e. ZZ /\\ B e. ( ZZ>= ` ( 1 + 1 ) ) ) -> 1 < B ) |\n| 13 | 7, 11, 12 | #P_sylancr | |- ( ( B e. ( ZZ>= ` 2 ) /\\ X e. RR+ /\\ Y e. RR+ ) -> 1 < B ) |\n| 14 | 6, 13 | #P_rplogcld | |- ( ( B e. ( ZZ>= ` 2 ) /\\ X e. RR+ /\\ Y e. RR+ ) -> ( log ` B ) e. RR+ ) |\n| 15 | 2, 4, 14 | #P_lediv1d | |- ( ( B e. ( ZZ>= ` 2 ) /\\ X e. RR+ /\\ Y e. RR+ ) -> ( ( log ` X ) <_ ( log ` Y ) <-> ( ( log ` X ) / ( log ` B ) ) <_ ( ( log ` Y ) / ( log ` B ) ) ) ) |\n| 16 |  | #P_logleb | |- ( ( X e. RR+ /\\ Y e. RR+ ) -> ( X <_ Y <-> ( log ` X ) <_ ( log ` Y ) ) ) |\n| 17 | 16 | #P_3adant1 | |- ( ( B e. ( ZZ>= ` 2 ) /\\ X e. RR+ /\\ Y e. RR+ ) -> ( X <_ Y <-> ( log ` X ) <_ ( log ` Y ) ) ) |\n| 18 |  | #P_relogbval | |- ( ( B e. ( ZZ>= ` 2 ) /\\ X e. RR+ ) -> ( B logb X ) = ( ( log ` X ) / ( log ` B ) ) ) |\n| 19 | 18 | #P_3adant3 | |- ( ( B e. ( ZZ>= ` 2 ) /\\ X e. RR+ /\\ Y e. RR+ ) -> ( B logb X ) = ( ( log ` X ) / ( log ` B ) ) ) |\n| 20 |  | #P_relogbval | |- ( ( B e. ( ZZ>= ` 2 ) /\\ Y e. RR+ ) -> ( B logb Y ) = ( ( log ` Y ) / ( log ` B ) ) ) |\n| 21 | 20 | #P_3adant2 | |- ( ( B e. ( ZZ>= ` 2 ) /\\ X e. RR+ /\\ Y e. RR+ ) -> ( B logb Y ) = ( ( log ` Y ) / ( log ` B ) ) ) |\n| 22 | 19, 21 | #P_breq12d | |- ( ( B e. ( ZZ>= ` 2 ) /\\ X e. RR+ /\\ Y e. RR+ ) -> ( ( B logb X ) <_ ( B logb Y ) <-> ( ( log ` X ) / ( log ` B ) ) <_ ( ( log ` Y ) / ( log ` B ) ) ) ) |\n| 23 | 15, 17, 22 | #P_3bitr4d | |- ( ( B e. ( ZZ>= ` 2 ) /\\ X e. RR+ /\\ Y e. RR+ ) -> ( X <_ Y <-> ( B logb X ) <_ ( B logb Y ) ) ) |",
  "conclusion" : "#P_logbleb",
  "language" : "METAMATH_SET_MM",
  "lookupTerms" : [ "#T_cB.wceq", "#T_wcel", "#T_cuz", "#T_cfv", "#T_c2", "#T_w3a--1", "#T_cX", "#T_wcel", "#T_crp", "#T_w3a--2", "#T_cY", "#T_wcel", "#T_crp", "#T_wi", "#T_cX", "#T_wcel", "#T_crp", "#T_cB.wceq", "#T_wcel", "#T_cuz", "#T_cfv", "#T_c2", "#T_w3a--1", "#T_cX", "#T_wcel", "#T_crp", "#T_w3a--2", "#T_cY", "#T_wcel", "#T_crp", "#T_wi", "#T_clog", "#T_cfv", "#T_cX", "#T_wcel", "#T_cr", "#T_cB.wceq", "#T_wcel", "#T_cuz", "#T_cfv", "#T_c2", "#T_w3a--1", "#T_cX", "#T_wcel", "#T_crp", "#T_w3a--2", "#T_cY", "#T_wcel", "#T_crp", "#T_wi", "#T_cY", "#T_wcel", "#T_crp", "#T_cB.wceq", "#T_wcel", "#T_cuz", "#T_cfv", "#T_c2", "#T_w3a--1", "#T_cX", "#T_wcel", "#T_crp", "#T_w3a--2", "#T_cY", "#T_wcel", "#T_crp", "#T_wi", "#T_clog", "#T_cfv", "#T_cY", "#T_wcel", "#T_cr", "#T_cB.wceq", "#T_wcel", "#T_cuz", "#T_cfv", "#T_c2", "#T_wi", "#T_cB.wceq", "#T_wcel", "#T_cr", "#T_cB.wceq", "#T_wcel", "#T_cuz", "#T_cfv", "#T_c2", "#T_w3a--1", "#T_cX", "#T_wcel", "#T_crp", "#T_w3a--2", "#T_cY", "#T_wcel", "#T_crp", "#T_wi", "#T_cB.wceq", "#T_wcel", "#T_cr", "#T_c1", "#T_wcel", "#T_cz", "#T_cB.wceq", "#T_wcel", "#T_cuz", "#T_cfv", "#T_c2", "#T_w3a--1", "#T_cX", "#T_wcel", "#T_crp", "#T_w3a--2", "#T_cY", "#T_wcel", "#T_crp", "#T_wi", "#T_cB.wceq", "#T_wcel", "#T_cuz", "#T_cfv", "#T_c2", "#T_c1", "#T_caddc", "#T_c1", "#T_wceq", "#T_c2", "#T_cuz", "#T_cfv", "#T_c1", "#T_caddc", "#T_c1", "#T_wceq", "#T_cuz", "#T_cfv", "#T_c2", "#T_cB.wceq", "#T_wcel", "#T_cuz", "#T_cfv", "#T_c2", "#T_w3a--1", "#T_cX", "#T_wcel", "#T_crp", "#T_w3a--2", "#T_cY", "#T_wcel", "#T_crp", "#T_wi", "#T_cB.wceq", "#T_wcel", "#T_cuz", "#T_cfv", "#T_c1", "#T_caddc", "#T_c1", "#T_c1", "#T_wcel", "#T_cz", "#T_wa", "#T_cB.wceq", "#T_wcel", "#T_cuz", "#T_cfv", "#T_c1", "#T_caddc", "#T_c1", "#T_wi", "#T_c1", "#T_clt", "#T_cB.wceq", "#T_cB.wceq", "#T_wcel", "#T_cuz", "#T_cfv", "#T_c2", "#T_w3a--1", "#T_cX", "#T_wcel", "#T_crp", "#T_w3a--2", "#T_cY", "#T_wcel", "#T_crp", "#T_wi", "#T_c1", "#T_clt", "#T_cB.wceq", "#T_cB.wceq", "#T_wcel", "#T_cuz", "#T_cfv", "#T_c2", "#T_w3a--1", "#T_cX", "#T_wcel", "#T_crp", "#T_w3a--2", "#T_cY", "#T_wcel", "#T_crp", "#T_wi", "#T_clog", "#T_cfv", "#T_cB.wceq", "#T_wcel", "#T_crp", "#T_cB.wceq", "#T_wcel", "#T_cuz", "#T_cfv", "#T_c2", "#T_w3a--1", "#T_cX", "#T_wcel", "#T_crp", "#T_w3a--2", "#T_cY", "#T_wcel", "#T_crp", "#T_wi", "#T_clog", "#T_cfv", "#T_cX", "#T_cle", "#T_clog", "#T_cfv", "#T_cY", "#T_wb", "#T_clog", "#T_cfv", "#T_cX", "#T_cdiv", "#T_clog", "#T_cfv", "#T_cB.wceq", "#T_cle", "#T_clog", "#T_cfv", "#T_cY", "#T_cdiv", "#T_clog", "#T_cfv", "#T_cB.wceq", "#T_cX", "#T_wcel", "#T_crp", "#T_wa", "#T_cY", "#T_wcel", "#T_crp", "#T_wi", "#T_cX", "#T_cle", "#T_cY", "#T_wb", "#T_clog", "#T_cfv", "#T_cX", "#T_cle", "#T_clog", "#T_cfv", "#T_cY", "#T_cB.wceq", "#T_wcel", "#T_cuz", "#T_cfv", "#T_c2", "#T_w3a--1", "#T_cX", "#T_wcel", "#T_crp", "#T_w3a--2", "#T_cY", "#T_wcel", "#T_crp", "#T_wi", "#T_cX", "#T_cle", "#T_cY", "#T_wb", "#T_clog", "#T_cfv", "#T_cX", "#T_cle", "#T_clog", "#T_cfv", "#T_cY", "#T_cB.wceq", "#T_wcel", "#T_cuz", "#T_cfv", "#T_c2", "#T_wa", "#T_cX", "#T_wcel", "#T_crp", "#T_wi", "#T_cB.wceq", "#T_clogb", "#T_cX", "#T_wceq", "#T_clog", "#T_cfv", "#T_cX", "#T_cdiv", "#T_clog", "#T_cfv", "#T_cB.wceq", "#T_cB.wceq", "#T_wcel", "#T_cuz", "#T_cfv", "#T_c2", "#T_w3a--1", "#T_cX", "#T_wcel", "#T_crp", "#T_w3a--2", "#T_cY", "#T_wcel", "#T_crp", "#T_wi", "#T_cB.wceq", "#T_clogb", "#T_cX", "#T_wceq", "#T_clog", "#T_cfv", "#T_cX", "#T_cdiv", "#T_clog", "#T_cfv", "#T_cB.wceq", "#T_cB.wceq", "#T_wcel", "#T_cuz", "#T_cfv", "#T_c2", "#T_wa", "#T_cY", "#T_wcel", "#T_crp", "#T_wi", "#T_cB.wceq", "#T_clogb", "#T_cY", "#T_wceq", "#T_clog", "#T_cfv", "#T_cY", "#T_cdiv", "#T_clog", "#T_cfv", "#T_cB.wceq", "#T_cB.wceq", "#T_wcel", "#T_cuz", "#T_cfv", "#T_c2", "#T_w3a--1", "#T_cX", "#T_wcel", "#T_crp", "#T_w3a--2", "#T_cY", "#T_wcel", "#T_crp", "#T_wi", "#T_cB.wceq", "#T_clogb", "#T_cY", "#T_wceq", "#T_clog", "#T_cfv", "#T_cY", "#T_cdiv", "#T_clog", "#T_cfv", "#T_cB.wceq", "#T_cB.wceq", "#T_wcel", "#T_cuz", "#T_cfv", "#T_c2", "#T_w3a--1", "#T_cX", "#T_wcel", "#T_crp", "#T_w3a--2", "#T_cY", "#T_wcel", "#T_crp", "#T_wi", "#T_cB.wceq", "#T_clogb", "#T_cX", "#T_cle", "#T_cB.wceq", "#T_clogb", "#T_cY", "#T_wb", "#T_clog", "#T_cfv", "#T_cX", "#T_cdiv", "#T_clog", "#T_cfv", "#T_cB.wceq", "#T_cle", "#T_clog", "#T_cfv", "#T_cY", "#T_cdiv", "#T_clog", "#T_cfv", "#T_cB.wceq", "#T_cB", "#T_wcel", "#T_cuz", "#T_cfv", "#T_c2", "#T_w3a--1", "#T_cX", "#T_wcel", "#T_crp", "#T_w3a--2", "#T_cY", "#T_wcel", "#T_crp", "#T_wi", "#T_cX", "#T_cle", "#T_cY", "#T_wb", "#T_cB", "#T_clogb", "#T_cX", "#T_cle", "#T_cB", "#T_clogb", "#T_cY" ],
  "metaLanguage" : "METAMATH",
  "premises" : [ "#P_fveq2i", "#P_3adant2", "#P_3adant1", "#P_3bitr4d", "#P_1z", "#P_relogbval", "#P_syl6eleqr", "#P_eluzp1l", "#P_relogcld", "#P_3ad2ant1", "#P_lediv1d", "#P_1p1e2", "#P_sylancr", "#P_rplogcld", "#P_simp3", "#P_logleb", "#P_simp2", "#P_eluzelre", "#P_simp1", "#P_breq12d", "#P_3adant3" ]
}