{
  "citations" : [ {
    "textCitation" : "[See lshpkr on Metamath](http://us.metamath.org/mpegif/lshpkr.html)"
  } ],
  "argumentText" : "ARGUMENT\nv\n\n| Step | Hyp | Ref | Expression |\n|---|---|---|---|\n\n| 1 |  | lshpkr.v | |- V = ( Base ` W ) |\n| 2 |  | lshpkr.a | |- .+ = ( +g ` W ) |\n| 3 |  | lshpkr.n | |- N = ( LSpan ` W ) |\n| 4 |  | lshpkr.p | |- .(+) = ( LSSum ` W ) |\n| 5 |  | lshpkr.h | |- H = ( LSHyp ` W ) |\n| 6 |  | lshpkr.w | |- ( ph -> W e. LVec ) |\n| 7 |  | lshpkr.u | |- ( ph -> U e. H ) |\n| 8 |  | lshpkr.z | |- ( ph -> Z e. V ) |\n| 9 |  | lshpkr.e | |- ( ph -> ( U .(+) ( N ` { Z } ) ) = V ) |\n| 10 |  | lshpkr.d | |- D = ( Scalar ` W ) |\n| 11 |  | lshpkr.k | |- K = ( Base ` D ) |\n| 12 |  | lshpkr.t | |- .x. = ( .s ` W ) |\n| 13 |  | lshpkr.g | |- G = ( x e. V |-> ( iota_ k e. K E. y e. U x = ( y .+ ( k .x. Z ) ) ) ) |\n| 14 |  | lshpkr.l | |- L = ( LKer ` W ) |\n| 15 |  | #P_eqid | |- ( LFnl ` W ) = ( LFnl ` W ) |\n| 16 |  | #P_lveclmod | |- ( W e. LVec -> W e. LMod ) |\n| 17 | 6, 16 | #P_syl | |- ( ph -> W e. LMod ) |\n| 18 | 1, 2, 3, 4, 5, 6, 7, 8, 9, 10, 11, 12, 13, 15 | #P_lshpkrcl | |- ( ph -> G e. ( LFnl ` W ) ) |\n| 19 | 1, 15, 14, 17, 18 | #P_lkrssv | |- ( ph -> ( L ` G ) C_ V ) |\n| 20 | 19 | #P_sseld | |- ( ph -> ( v e. ( L ` G ) -> v e. V ) ) |\n| 21 |  | #P_eqid | |- ( LSubSp ` W ) = ( LSubSp ` W ) |\n| 22 | 21, 5, 17, 7 | #P_lshplss | |- ( ph -> U e. ( LSubSp ` W ) ) |\n| 23 | 1, 21 | #P_lssel | |- ( ( U e. ( LSubSp ` W ) /\\ v e. U ) -> v e. V ) |\n| 24 | 22, 23 | #P_sylan | |- ( ( ph /\\ v e. U ) -> v e. V ) |\n| 25 | 24 | #P_ex | |- ( ph -> ( v e. U -> v e. V ) ) |\n| 26 |  | #P_eqid | |- ( 0g ` D ) = ( 0g ` D ) |\n| 27 | 1, 10, 26, 15, 14 | #P_ellkr | |- ( ( W e. LVec /\\ G e. ( LFnl ` W ) ) -> ( v e. ( L ` G ) <-> ( v e. V /\\ ( G ` v ) = ( 0g ` D ) ) ) ) |\n| 28 | 6, 18, 27 | #P_syl2anc | |- ( ph -> ( v e. ( L ` G ) <-> ( v e. V /\\ ( G ` v ) = ( 0g ` D ) ) ) ) |\n| 29 | 28 | #P_baibd | |- ( ( ph /\\ v e. V ) -> ( v e. ( L ` G ) <-> ( G ` v ) = ( 0g ` D ) ) ) |\n| 30 | 6 | #P_adantr | |- ( ( ph /\\ v e. V ) -> W e. LVec ) |\n| 31 | 7 | #P_adantr | |- ( ( ph /\\ v e. V ) -> U e. H ) |\n| 32 | 8 | #P_adantr | |- ( ( ph /\\ v e. V ) -> Z e. V ) |\n| 33 |  | #P_simpr | |- ( ( ph /\\ v e. V ) -> v e. V ) |\n| 34 | 9 | #P_adantr | |- ( ( ph /\\ v e. V ) -> ( U .(+) ( N ` { Z } ) ) = V ) |\n| 35 | 1, 2, 3, 4, 5, 30, 31, 32, 33, 34, 10, 11, 12, 26, 13 | #P_lshpkrlem1 | |- ( ( ph /\\ v e. V ) -> ( v e. U <-> ( G ` v ) = ( 0g ` D ) ) ) |\n| 36 | 29, 35 | #P_bitr4d | |- ( ( ph /\\ v e. V ) -> ( v e. ( L ` G ) <-> v e. U ) ) |\n| 37 | 36 | #P_ex | |- ( ph -> ( v e. V -> ( v e. ( L ` G ) <-> v e. U ) ) ) |\n| 38 | 20, 25, 37 | #P_pm5.21ndd | |- ( ph -> ( v e. ( L ` G ) <-> v e. U ) ) |\n| 39 | 38 | #P_eqrdv | |- ( ph -> ( L ` G ) = U ) |",
  "conclusion" : "#P_lshpkr",
  "language" : "METAMATH_SET_MM",
  "lookupTerms" : [ "#T_vv", "#T_cV", "#T_wceq", "#T_cbs", "#T_cfv", "#T_cW", "#T_c.pl", "#T_wceq", "#T_cplusg", "#T_cfv", "#T_cW", "#T_cN", "#T_wceq", "#T_clspn", "#T_cfv", "#T_cW", "#T_c.po", "#T_wceq", "#T_clsm", "#T_cfv", "#T_cW", "#T_cH", "#T_wceq", "#T_clsh", "#T_cfv", "#T_cW", "#T_wph", "#T_wi", "#T_cW", "#T_wcel", "#T_clvec", "#T_wph", "#T_wi", "#T_cU", "#T_wcel", "#T_cH", "#T_wph", "#T_wi", "#T_cZ", "#T_wcel", "#T_cV", "#T_wph", "#T_wi", "#T_cU", "#T_c.po", "#T_cN", "#T_cfv", "#T_csn--1", "#T_cZ", "#T_csn--2", "#T_wceq", "#T_cV", "#T_cD", "#T_wceq", "#T_csca", "#T_cfv", "#T_cW", "#T_cK", "#T_wceq", "#T_cbs", "#T_cfv", "#T_cD", "#T_c.x", "#T_wceq", "#T_cvsca", "#T_cfv", "#T_cW", "#T_cG", "#T_wceq", "#T_vx", "#T_cmpt--1", "#T_cV", "#T_cmpt--2", "#T_crio--1", "#T_vk", "#T_crio--2", "#T_cK", "#T_wrex--1", "#T_vy", "#T_wrex--2", "#T_cU", "#T_vx", "#T_wceq", "#T_vy", "#T_c.pl", "#T_vk", "#T_c.x", "#T_cZ", "#T_cL", "#T_wceq", "#T_clk", "#T_cfv", "#T_cW", "#T_clfn", "#T_cfv", "#T_cW", "#T_wceq", "#T_clfn", "#T_cfv", "#T_cW", "#T_cW", "#T_wcel", "#T_clvec", "#T_wi", "#T_cW", "#T_wcel", "#T_clmod", "#T_wph", "#T_wi", "#T_cW", "#T_wcel", "#T_clmod", "#T_wph", "#T_wi", "#T_cG", "#T_wcel", "#T_clfn", "#T_cfv", "#T_cW", "#T_wph", "#T_wi", "#T_cL", "#T_cfv", "#T_cG", "#T_wss", "#T_cV", "#T_wph", "#T_wi", "#T_vv", "#T_wcel", "#T_cL", "#T_cfv", "#T_cG", "#T_wi", "#T_vv", "#T_wcel", "#T_cV", "#T_clss", "#T_cfv", "#T_cW", "#T_wceq", "#T_clss", "#T_cfv", "#T_cW", "#T_wph", "#T_wi", "#T_cU", "#T_wcel", "#T_clss", "#T_cfv", "#T_cW", "#T_cU", "#T_wcel", "#T_clss", "#T_cfv", "#T_cW", "#T_wa", "#T_vv", "#T_wcel", "#T_cU", "#T_wi", "#T_vv", "#T_wcel", "#T_cV", "#T_wph", "#T_wa", "#T_vv", "#T_wcel", "#T_cU", "#T_wi", "#T_vv", "#T_wcel", "#T_cV", "#T_wph", "#T_wi", "#T_vv", "#T_wcel", "#T_cU", "#T_wi", "#T_vv", "#T_wcel", "#T_cV", "#T_c0g", "#T_cfv", "#T_cD", "#T_wceq", "#T_c0g", "#T_cfv", "#T_cD", "#T_cW", "#T_wcel", "#T_clvec", "#T_wa", "#T_cG", "#T_wcel", "#T_clfn", "#T_cfv", "#T_cW", "#T_wi", "#T_vv", "#T_wcel", "#T_cL", "#T_cfv", "#T_cG", "#T_wb", "#T_vv", "#T_wcel", "#T_cV", "#T_wa", "#T_cG", "#T_cfv", "#T_vv", "#T_wceq", "#T_c0g", "#T_cfv", "#T_cD", "#T_wph", "#T_wi", "#T_vv", "#T_wcel", "#T_cL", "#T_cfv", "#T_cG", "#T_wb", "#T_vv", "#T_wcel", "#T_cV", "#T_wa", "#T_cG", "#T_cfv", "#T_vv", "#T_wceq", "#T_c0g", "#T_cfv", "#T_cD", "#T_wph", "#T_wa", "#T_vv", "#T_wcel", "#T_cV", "#T_wi", "#T_vv", "#T_wcel", "#T_cL", "#T_cfv", "#T_cG", "#T_wb", "#T_cG", "#T_cfv", "#T_vv", "#T_wceq", "#T_c0g", "#T_cfv", "#T_cD", "#T_wph", "#T_wa", "#T_vv", "#T_wcel", "#T_cV", "#T_wi", "#T_cW", "#T_wcel", "#T_clvec", "#T_wph", "#T_wa", "#T_vv", "#T_wcel", "#T_cV", "#T_wi", "#T_cU", "#T_wcel", "#T_cH", "#T_wph", "#T_wa", "#T_vv", "#T_wcel", "#T_cV", "#T_wi", "#T_cZ", "#T_wcel", "#T_cV", "#T_wph", "#T_wa", "#T_vv", "#T_wcel", "#T_cV", "#T_wi", "#T_vv", "#T_wcel", "#T_cV", "#T_wph", "#T_wa", "#T_vv", "#T_wcel", "#T_cV", "#T_wi", "#T_cU", "#T_c.po", "#T_cN", "#T_cfv", "#T_csn--1", "#T_cZ", "#T_csn--2", "#T_wceq", "#T_cV", "#T_wph", "#T_wa", "#T_vv", "#T_wcel", "#T_cV", "#T_wi", "#T_vv", "#T_wcel", "#T_cU", "#T_wb", "#T_cG", "#T_cfv", "#T_vv", "#T_wceq", "#T_c0g", "#T_cfv", "#T_cD", "#T_wph", "#T_wa", "#T_vv", "#T_wcel", "#T_cV", "#T_wi", "#T_vv", "#T_wcel", "#T_cL", "#T_cfv", "#T_cG", "#T_wb", "#T_vv", "#T_wcel", "#T_cU", "#T_wph", "#T_wi", "#T_vv", "#T_wcel", "#T_cV", "#T_wi", "#T_vv", "#T_wcel", "#T_cL", "#T_cfv", "#T_cG", "#T_wb", "#T_vv", "#T_wcel", "#T_cU", "#T_wph", "#T_wi", "#T_vv", "#T_wcel", "#T_cL", "#T_cfv", "#T_cG", "#T_wb", "#T_vv", "#T_wcel", "#T_cU", "#T_wph", "#T_wi", "#T_cL", "#T_cfv", "#T_cG", "#T_wceq", "#T_cU" ],
  "metaLanguage" : "METAMATH",
  "premises" : [ "#P_ellkr", "#P_lshplss", "#P_sylan", "#P_bitr4d", "#P_sseld", "#P_lveclmod", "#P_lshpkrcl", "#P_lshpkrlem1", "#P_baibd", "#P_eqid", "#P_pm5.21ndd", "#P_syl2anc", "#P_ex", "#P_lkrssv", "#P_syl", "#P_simpr", "#P_eqrdv", "#P_lssel", "#P_adantr" ]
}