{
  "citations" : [ {
    "textCitation" : "[See onminesb on Metamath](http://us.metamath.org/mpegif/onminesb.html)"
  } ],
  "argumentText" : "ARGUMENT\n\n| Step | Hyp | Ref | Expression |\n|---|---|---|---|\n\n| 1 |  | #P_rabn0 | |- ( { x e. On | ph } =/= (/) <-> E. x e. On ph ) |\n| 2 |  | #P_ssrab2 | |- { x e. On | ph } C_ On |\n| 3 |  | #P_onint | |- ( ( { x e. On | ph } C_ On /\\ { x e. On | ph } =/= (/) ) -> |^| { x e. On | ph } e. { x e. On | ph } ) |\n| 4 | 2, 3 | #P_mpan | |- ( { x e. On | ph } =/= (/) -> |^| { x e. On | ph } e. { x e. On | ph } ) |\n| 5 | 1, 4 | #P_sylbir | |- ( E. x e. On ph -> |^| { x e. On | ph } e. { x e. On | ph } ) |\n| 6 |  | #P_nfcv | |- F/_ x On |\n| 7 | 6 | #P_elrabsf | |- ( |^| { x e. On | ph } e. { x e. On | ph } <-> ( |^| { x e. On | ph } e. On /\\ [. |^| { x e. On | ph } / x ]. ph ) ) |\n| 8 | 7 | #P_simprbi | |- ( |^| { x e. On | ph } e. { x e. On | ph } -> [. |^| { x e. On | ph } / x ]. ph ) |\n| 9 | 5, 8 | #P_syl | |- ( E. x e. On ph -> [. |^| { x e. On | ph } / x ]. ph ) |",
  "conclusion" : "#P_onminesb",
  "language" : "METAMATH_SET_MM",
  "lookupTerms" : [ "#T_crab--1", "#T_vx.wal", "#T_crab--2", "#T_con0", "#T_crab--3", "#T_wph", "#T_crab--4", "#T_wne", "#T_c0", "#T_wb", "#T_wrex--1", "#T_vx.wal", "#T_wrex--2", "#T_con0", "#T_wph", "#T_crab--1", "#T_vx.wal", "#T_crab--2", "#T_con0", "#T_crab--3", "#T_wph", "#T_crab--4", "#T_wss", "#T_con0", "#T_crab--1", "#T_vx.wal", "#T_crab--2", "#T_con0", "#T_crab--3", "#T_wph", "#T_crab--4", "#T_wss", "#T_con0", "#T_wa", "#T_crab--1", "#T_vx.wal", "#T_crab--2", "#T_con0", "#T_crab--3", "#T_wph", "#T_crab--4", "#T_wne", "#T_c0", "#T_wi", "#T_cint", "#T_crab--1", "#T_vx.wal", "#T_crab--2", "#T_con0", "#T_crab--3", "#T_wph", "#T_crab--4", "#T_wcel", "#T_crab--1", "#T_vx.wal", "#T_crab--2", "#T_con0", "#T_crab--3", "#T_wph", "#T_crab--4", "#T_crab--1", "#T_vx.wal", "#T_crab--2", "#T_con0", "#T_crab--3", "#T_wph", "#T_crab--4", "#T_wne", "#T_c0", "#T_wi", "#T_cint", "#T_crab--1", "#T_vx.wal", "#T_crab--2", "#T_con0", "#T_crab--3", "#T_wph", "#T_crab--4", "#T_wcel", "#T_crab--1", "#T_vx.wal", "#T_crab--2", "#T_con0", "#T_crab--3", "#T_wph", "#T_crab--4", "#T_wrex--1", "#T_vx.wal", "#T_wrex--2", "#T_con0", "#T_wph", "#T_wi", "#T_cint", "#T_crab--1", "#T_vx.wal", "#T_crab--2", "#T_con0", "#T_crab--3", "#T_wph", "#T_crab--4", "#T_wcel", "#T_crab--1", "#T_vx.wal", "#T_crab--2", "#T_con0", "#T_crab--3", "#T_wph", "#T_crab--4", "#T_wnfc", "#T_vx.wal", "#T_con0", "#T_cint", "#T_crab--1", "#T_vx.wal", "#T_crab--2", "#T_con0", "#T_crab--3", "#T_wph", "#T_crab--4", "#T_wcel", "#T_crab--1", "#T_vx.wal", "#T_crab--2", "#T_con0", "#T_crab--3", "#T_wph", "#T_crab--4", "#T_wb", "#T_cint", "#T_crab--1", "#T_vx.wal", "#T_crab--2", "#T_con0", "#T_crab--3", "#T_wph", "#T_crab--4", "#T_wcel", "#T_con0", "#T_wa", "#T_wsbc--1", "#T_cint", "#T_crab--1", "#T_vx.wal", "#T_crab--2", "#T_con0", "#T_crab--3", "#T_wph", "#T_crab--4", "#T_wsbc--2", "#T_vx.wal", "#T_wsbc--3", "#T_wph", "#T_cint", "#T_crab--1", "#T_vx.wal", "#T_crab--2", "#T_con0", "#T_crab--3", "#T_wph", "#T_crab--4", "#T_wcel", "#T_crab--1", "#T_vx.wal", "#T_crab--2", "#T_con0", "#T_crab--3", "#T_wph", "#T_crab--4", "#T_wi", "#T_wsbc--1", "#T_cint", "#T_crab--1", "#T_vx.wal", "#T_crab--2", "#T_con0", "#T_crab--3", "#T_wph", "#T_crab--4", "#T_wsbc--2", "#T_vx.wal", "#T_wsbc--3", "#T_wph", "#T_wrex--1", "#T_vx", "#T_wrex--2", "#T_con0", "#T_wph", "#T_wi", "#T_wsbc--1", "#T_cint", "#T_crab--1", "#T_vx", "#T_crab--2", "#T_con0", "#T_crab--3", "#T_wph", "#T_crab--4", "#T_wsbc--2", "#T_vx", "#T_wsbc--3", "#T_wph" ],
  "metaLanguage" : "METAMATH",
  "premises" : [ "#P_ssrab2", "#P_nfcv", "#P_simprbi", "#P_sylbir", "#P_onint", "#P_mpan", "#P_syl", "#P_elrabsf", "#P_rabn0" ]
}