{
  "citations" : [ {
    "textCitation" : "[See pm13.192 on Metamath](http://us.metamath.org/mpegif/pm13.192.html)"
  } ],
  "argumentText" : "ARGUMENT\n\n| Step | Hyp | Ref | Expression |\n|---|---|---|---|\n\n| 1 |  | #P_bi2 | |- ( ( x = A <-> x = y ) -> ( x = y -> x = A ) ) |\n| 2 | 1 | #P_alimi | |- ( A. x ( x = A <-> x = y ) -> A. x ( x = y -> x = A ) ) |\n| 3 |  | #P_nfv | |- F/ x y = A |\n| 4 |  | #P_eqeq1 | |- ( x = y -> ( x = A <-> y = A ) ) |\n| 5 | 3, 4 | #P_equsal | |- ( A. x ( x = y -> x = A ) <-> y = A ) |\n| 6 | 2, 5 | #P_sylib | |- ( A. x ( x = A <-> x = y ) -> y = A ) |\n| 7 |  | #P_eqeq2 | |- ( A = y -> ( x = A <-> x = y ) ) |\n| 8 | 7 | #P_eqcoms | |- ( y = A -> ( x = A <-> x = y ) ) |\n| 9 | 8 | #P_alrimiv | |- ( y = A -> A. x ( x = A <-> x = y ) ) |\n| 10 | 6, 9 | #P_impbii | |- ( A. x ( x = A <-> x = y ) <-> y = A ) |\n| 11 | 10 | #P_anbi1i | |- ( ( A. x ( x = A <-> x = y ) /\\ ph ) <-> ( y = A /\\ ph ) ) |\n| 12 | 11 | #P_exbii | |- ( E. y ( A. x ( x = A <-> x = y ) /\\ ph ) <-> E. y ( y = A /\\ ph ) ) |\n| 13 |  | #P_sbc5 | |- ( [. A / y ]. ph <-> E. y ( y = A /\\ ph ) ) |\n| 14 | 12, 13 | #P_bitr4i | |- ( E. y ( A. x ( x = A <-> x = y ) /\\ ph ) <-> [. A / y ]. ph ) |",
  "conclusion" : "#P_pm13.192",
  "language" : "METAMATH_SET_MM",
  "lookupTerms" : [ "#T_vx.wal", "#T_wceq", "#T_cA.wceq", "#T_wb", "#T_vx.wal", "#T_wceq", "#T_vy.tru", "#T_wi", "#T_vx.wal", "#T_wceq", "#T_vy.tru", "#T_wi", "#T_vx.wal", "#T_wceq", "#T_cA.wceq", "#T_wal", "#T_vx.wal", "#T_vx.wal", "#T_wceq", "#T_cA.wceq", "#T_wb", "#T_vx.wal", "#T_wceq", "#T_vy.tru", "#T_wi", "#T_wal", "#T_vx.wal", "#T_vx.wal", "#T_wceq", "#T_vy.tru", "#T_wi", "#T_vx.wal", "#T_wceq", "#T_cA.wceq", "#T_wnf", "#T_vx.wal", "#T_vy.tru", "#T_wceq", "#T_cA.wceq", "#T_vx.wal", "#T_wceq", "#T_vy.tru", "#T_wi", "#T_vx.wal", "#T_wceq", "#T_cA.wceq", "#T_wb", "#T_vy.tru", "#T_wceq", "#T_cA.wceq", "#T_wal", "#T_vx.wal", "#T_vx.wal", "#T_wceq", "#T_vy.tru", "#T_wi", "#T_vx.wal", "#T_wceq", "#T_cA.wceq", "#T_wb", "#T_vy.tru", "#T_wceq", "#T_cA.wceq", "#T_wal", "#T_vx.wal", "#T_vx.wal", "#T_wceq", "#T_cA.wceq", "#T_wb", "#T_vx.wal", "#T_wceq", "#T_vy.tru", "#T_wi", "#T_vy.tru", "#T_wceq", "#T_cA.wceq", "#T_cA.wceq", "#T_wceq", "#T_vy.tru", "#T_wi", "#T_vx.wal", "#T_wceq", "#T_cA.wceq", "#T_wb", "#T_vx.wal", "#T_wceq", "#T_vy.tru", "#T_vy.tru", "#T_wceq", "#T_cA.wceq", "#T_wi", "#T_vx.wal", "#T_wceq", "#T_cA.wceq", "#T_wb", "#T_vx.wal", "#T_wceq", "#T_vy.tru", "#T_vy.tru", "#T_wceq", "#T_cA.wceq", "#T_wi", "#T_wal", "#T_vx.wal", "#T_vx.wal", "#T_wceq", "#T_cA.wceq", "#T_wb", "#T_vx.wal", "#T_wceq", "#T_vy.tru", "#T_wal", "#T_vx.wal", "#T_vx.wal", "#T_wceq", "#T_cA.wceq", "#T_wb", "#T_vx.wal", "#T_wceq", "#T_vy.tru", "#T_wb", "#T_vy.tru", "#T_wceq", "#T_cA.wceq", "#T_wal", "#T_vx.wal", "#T_vx.wal", "#T_wceq", "#T_cA.wceq", "#T_wb", "#T_vx.wal", "#T_wceq", "#T_vy.tru", "#T_wa", "#T_wph", "#T_wb", "#T_vy.tru", "#T_wceq", "#T_cA.wceq", "#T_wa", "#T_wph", "#T_wex", "#T_vy.tru", "#T_wal", "#T_vx.wal", "#T_vx.wal", "#T_wceq", "#T_cA.wceq", "#T_wb", "#T_vx.wal", "#T_wceq", "#T_vy.tru", "#T_wa", "#T_wph", "#T_wb", "#T_wex", "#T_vy.tru", "#T_vy.tru", "#T_wceq", "#T_cA.wceq", "#T_wa", "#T_wph", "#T_wsbc--1", "#T_cA.wceq", "#T_wsbc--2", "#T_vy.tru", "#T_wsbc--3", "#T_wph", "#T_wb", "#T_wex", "#T_vy.tru", "#T_vy.tru", "#T_wceq", "#T_cA.wceq", "#T_wa", "#T_wph", "#T_wex", "#T_vy", "#T_wal", "#T_vx", "#T_vx", "#T_wceq", "#T_cA", "#T_wb", "#T_vx", "#T_wceq", "#T_vy", "#T_wa", "#T_wph", "#T_wb", "#T_wsbc--1", "#T_cA", "#T_wsbc--2", "#T_vy", "#T_wsbc--3", "#T_wph" ],
  "metaLanguage" : "METAMATH",
  "premises" : [ "#P_nfv", "#P_impbii", "#P_exbii", "#P_sylib", "#P_alimi", "#P_bitr4i", "#P_bi2", "#P_eqeq2", "#P_anbi1i", "#P_equsal", "#P_eqcoms", "#P_alrimiv", "#P_eqeq1", "#P_sbc5" ]
}