{
  "citations" : [ {
    "textCitation" : "[See relopab on Metamath](http://us.metamath.org/mpegif/relopab.html)"
  } ],
  "argumentText" : "ARGUMENT\n\n| Step | Hyp | Ref | Expression |\n|---|---|---|---|\n\n| 1 |  | #P_eqid | |- { <. x , y >. | ph } = { <. x , y >. | ph } |\n| 2 | 1 | #P_relopabi | |- Rel { <. x , y >. | ph } |",
  "conclusion" : "#P_relopab",
  "language" : "METAMATH_SET_MM",
  "lookupTerms" : [ "#T_copab--1", "#T_copab--2", "#T_vx.wal", "#T_copab--3", "#T_vy.tru", "#T_copab--4", "#T_copab--5", "#T_wph", "#T_copab--6", "#T_wceq", "#T_copab--1", "#T_copab--2", "#T_vx.wal", "#T_copab--3", "#T_vy.tru", "#T_copab--4", "#T_copab--5", "#T_wph", "#T_copab--6", "#T_wrel", "#T_copab--1", "#T_copab--2", "#T_vx", "#T_copab--3", "#T_vy", "#T_copab--4", "#T_copab--5", "#T_wph", "#T_copab--6" ],
  "metaLanguage" : "METAMATH",
  "premises" : [ "#P_eqid", "#P_relopabi" ]
}