{
  "citations" : [ {
    "textCitation" : "[See 01sqrex on Metamath](http://us.metamath.org/mpegif/01sqrex.html)"
  } ],
  "names" : [ "01sqrex" ],
  "language" : "METAMATH_SET_MM",
  "lookupTerms" : [ "#T_cA", "#T_wcel", "#T_crp", "#T_wa", "#T_cA", "#T_cle", "#T_c1", "#T_wi", "#T_wrex--1", "#T_vx", "#T_wrex--2", "#T_crp", "#T_vx", "#T_cle", "#T_c1", "#T_wa", "#T_vx", "#T_cexp", "#T_c2", "#T_wceq", "#T_cA", "#T_cA", "#T_vx" ],
  "metaLanguage" : "METAMATH",
  "remarks" : " Existence of a square root for reals in the interval ` ( 0 , 1 ] ` . (Contributed by Mario Carneiro, 10-Jul-2013.) ",
  "statement" : "01sqrex $p |- ( ( A e. RR+ /\\ A <_ 1 ) -> E. x e. RR+ ( x <_ 1 /\\ ( x ^ 2 ) = A ) ) $.\n$d A x $."
}