{
  "citations" : [ {
    "textCitation" : "[See clmzlmvsca on Metamath](http://us.metamath.org/mpegif/clmzlmvsca.html)"
  } ],
  "names" : [ "clmzlmvsca" ],
  "language" : "METAMATH_SET_MM",
  "lookupTerms" : [ "#T_cW", "#T_wceq", "#T_czlm", "#T_cfv", "#T_cG", "#T_cX", "#T_wceq", "#T_cbs", "#T_cfv", "#T_cG", "#T_cG", "#T_wcel", "#T_cclm", "#T_wa", "#T_cA", "#T_wcel", "#T_cz", "#T_wa", "#T_cB", "#T_wcel", "#T_cX", "#T_wi", "#T_cA", "#T_cvsca", "#T_cfv", "#T_cG", "#T_cB", "#T_wceq", "#T_cA", "#T_cvsca", "#T_cfv", "#T_cW", "#T_cB" ],
  "metaLanguage" : "METAMATH",
  "remarks" : " The scalar product of a complex module matches the scalar product of the derived ` ZZ ` -module, which implies, together with ~ zlmbas and ~ zlmplusg , that any module over ` ZZ ` is structure-equivalent to the canonical ` ZZ ` -module ` ZMod `` G ` .  (Contributed by Mario Carneiro, 30-Oct-2015.) ",
  "statement" : "zlmclm.w $e |- W = ( ZMod ` G ) $.\nclmzlmvsca.x $e |- X = ( Base ` G ) $.\nclmzlmvsca $p |- ( ( G e. CMod /\\ ( A e. ZZ /\\ B e. X ) ) -> ( A ( .s ` G ) B ) = ( A ( .s ` W ) B ) ) $."
}