{
  "citations" : [ {
    "textCitation" : "[See fin2so on Metamath](http://us.metamath.org/mpegif/fin2so.html)"
  } ],
  "names" : [ "fin2so" ],
  "language" : "METAMATH_SET_MM",
  "lookupTerms" : [ "#T_cA", "#T_wcel", "#T_cfin2", "#T_wa", "#T_cR", "#T_wor", "#T_cA", "#T_wi", "#T_cA", "#T_wcel", "#T_cfn" ],
  "metaLanguage" : "METAMATH",
  "remarks" : " Any totally ordered Tarski-finite set is finite; in particular, no amorphous set can be ordered.  (Contributed by Brendan Leahy, 28-Jun-2019.) ",
  "statement" : "fin2so $p |- ( ( A e. Fin2 /\\ R Or A ) -> A e. Fin ) $."
}