{
  "citations" : [ {
    "textCitation" : "[See rhmsscmap on Metamath](http://us.metamath.org/mpegif/rhmsscmap.html)"
  } ],
  "names" : [ "rhmsscmap" ],
  "language" : "METAMATH_SET_MM",
  "lookupTerms" : [ "#T_wph", "#T_wi", "#T_cU", "#T_wcel", "#T_cV", "#T_wph", "#T_wi", "#T_cR", "#T_wceq", "#T_crg", "#T_cin", "#T_cU", "#T_wph", "#T_wi", "#T_crh", "#T_cres", "#T_cR", "#T_cxp", "#T_cR", "#T_cssc", "#T_vx", "#T_cmpt2--1", "#T_cU", "#T_cmpt2--2", "#T_vy", "#T_cmpt2--3", "#T_cU", "#T_cmpt2--4", "#T_cbs", "#T_cfv", "#T_vy", "#T_cmap", "#T_cbs", "#T_cfv", "#T_vx", "#T_cR", "#T_vx", "#T_vy", "#T_cU", "#T_vx", "#T_vy", "#T_wph", "#T_vx", "#T_vy" ],
  "metaLanguage" : "METAMATH",
  "remarks" : " The unital ring homomorphisms between unital rings (in a universe) are a subcategory subset of the mappings between base sets of extensible structures (in the same universe).  (Contributed by AV, 9-Mar-2020.) ",
  "statement" : "rhmsscmap.u $e |- ( ph -> U e. V ) $.\nrhmsscmap.r $e |- ( ph -> R = ( Ring i^i U ) ) $.\nrhmsscmap $p |- ( ph -> ( RingHom |` ( R X. R ) ) C_cat ( x e. U , y e. U |-> ( ( Base ` y ) ^m ( Base ` x ) ) ) ) $.\n$d R x y $.\n$d U x y $.\n$d ph x y $."
}