{
  "citations" : [ {
    "textCitation" : "[See xpopth on Metamath](http://us.metamath.org/mpegif/xpopth.html)"
  } ],
  "names" : [ "xpopth" ],
  "language" : "METAMATH_SET_MM",
  "lookupTerms" : [ "#T_cA", "#T_wcel", "#T_cC", "#T_cxp", "#T_cD", "#T_wa", "#T_cB", "#T_wcel", "#T_cR", "#T_cxp", "#T_cS", "#T_wi", "#T_c1st", "#T_cfv", "#T_cA", "#T_wceq", "#T_c1st", "#T_cfv", "#T_cB", "#T_wa", "#T_c2nd", "#T_cfv", "#T_cA", "#T_wceq", "#T_c2nd", "#T_cfv", "#T_cB", "#T_wb", "#T_cA", "#T_wceq", "#T_cB" ],
  "metaLanguage" : "METAMATH",
  "remarks" : " An ordered pair theorem for members of Cartesian products.  (Contributed by NM, 20-Jun-2007.) \n\n---\n\n An ordered pair theorem for members of cross products.  (Contributed by NM, 20-Jun-2007.) ",
  "statement" : "xpopth $p |- ( ( A e. ( C X. D ) /\\ B e. ( R X. S ) ) -> ( ( ( 1st ` A ) = ( 1st ` B ) /\\ ( 2nd ` A ) = ( 2nd ` B ) ) <-> A = B ) ) $."
}